zeroheliumkit-0.5.5.dist-info/METADATA
zeroheliumkit-0.5.5.dist-info/WHEEL
zeroheliumkit-0.5.5.dist-info/entry_points.txt
zeroheliumkit-0.5.5.dist-info/licenses/LICENSE
zeroheliumkit/.DS_Store
zeroheliumkit/__init__.py
zeroheliumkit/fem/__init__.py
zeroheliumkit/fem/fieldreader.py
zeroheliumkit/fem/freefemer.py
zeroheliumkit/fem/gmsher.py
zeroheliumkit/fem/heliumsurface.py
zeroheliumkit/fem/palacer.py
zeroheliumkit/helpers/__init__.py
zeroheliumkit/helpers/constants.py
zeroheliumkit/helpers/resonator_calc.py
zeroheliumkit/src/__init__.py
zeroheliumkit/src/anchors.py
zeroheliumkit/src/core.py
zeroheliumkit/src/errors.py
zeroheliumkit/src/fonts.py
zeroheliumkit/src/functions.py
zeroheliumkit/src/geometries.py
zeroheliumkit/src/importing.py
zeroheliumkit/src/plotting.py
zeroheliumkit/src/routing.py
zeroheliumkit/src/settings.py
zeroheliumkit/src/supercore.py
zeroheliumkit/src/utils.py
zeroheliumkit-0.5.5.dist-info/RECORD
