Metadata-Version: 2.4
Name: zeroheliumkit
Version: 0.5.5
Summary: --
Author-Email: Niyaz Beysengulov <nbeysengulov@eeroq.com>
License-Expression: MIT
License-File: LICENSE
Classifier: Programming Language :: Python :: 3
Classifier: Operating System :: OS Independent
Project-URL: Homepage, https://github.com/eeroqlab/zeroheliumkit
Requires-Python: >=3.11
